setup.py
gtoolkit/__init__.py
gtoolkit.egg-info/PKG-INFO
gtoolkit.egg-info/SOURCES.txt
gtoolkit.egg-info/dependency_links.txt
gtoolkit.egg-info/requires.txt
gtoolkit.egg-info/top_level.txt
gtoolkit/db/__init__.py
gtoolkit/db/kafka_conn.py
gtoolkit/db/mongo_conn.py
gtoolkit/db/redis_conn.py
gtoolkit/db/mysql/__init__.py
gtoolkit/db/mysql/orm/__init__.py
gtoolkit/db/mysql/orm/sqlalchemy/__init__.py
gtoolkit/db/mysql/orm/sqlalchemy/engine.py
gtoolkit/db/mysql/orm/sqlalchemy/methods.py
gtoolkit/db/orm/__init__.py
gtoolkit/db/orm/sqlalchemy/__init__.py
gtoolkit/db/orm/sqlalchemy/engine.py
gtoolkit/db/orm/sqlalchemy/exception.py
gtoolkit/db/orm/sqlalchemy/methods.py
gtoolkit/db/postgresql/__init__.py
gtoolkit/db/postgresql/orm/__init__.py
gtoolkit/db/postgresql/orm/sqlalchemy/__init__.py
gtoolkit/db/postgresql/orm/sqlalchemy/engine.py
gtoolkit/db/postgresql/orm/sqlalchemy/methods.py
gtoolkit/network/__init__.py
gtoolkit/network/ftp_helper.py
gtoolkit/network/linux_helper.py
gtoolkit/network/requests_helper.py
gtoolkit/network/upy_helper.py
gtoolkit/office/__init__.py
gtoolkit/office/excel.py
gtoolkit/utils/__init__.py
gtoolkit/utils/number.py
gtoolkit/utils/runjs.py
gtoolkit/utils/string.py
gtoolkit/utils/time.py
gtoolkit/utils/zip.py