Metadata-Version: 2.1
Name: gtoolkit
Version: 0.0.9
Summary: 一个工具集合
Author: 郭一会儿
Author-email: 1015295213@qq.com
License: MIT Licence
Keywords: gtoolkit
Platform: any
